{
    "experiment_name": "problem_100_0.85",
    "run_index": 15,
    "execution_time": 57.05,
    "final_objective": 471118.49,
    "final_routes": [
        [
            0,
            11,
            33,
            26,
            90,
            93,
            48,
            74,
            25,
            34,
            27,
            20,
            0
        ],
        [
            0,
            75,
            97,
            51,
            96,
            77,
            71,
            6,
            94,
            61,
            59,
            45,
            80,
            0
        ],
        [
            0,
            35,
            39,
            41,
            52,
            36,
            64,
            86,
            0
        ],
        [
            0,
            65,
            9,
            15,
            68,
            83,
            28,
            38,
            16,
            95,
            43,
            22,
            4,
            0
        ],
        [
            0,
            99,
            55,
            13,
            57,
            54,
            18,
            2,
            44,
            62,
            0
        ],
        [
            0,
            8,
            47,
            78,
            49,
            31,
            73,
            29,
            85,
            67,
            53,
            0
        ],
        [
            0,
            76,
            10,
            7,
            42,
            87,
            70,
            17,
            24,
            19,
            0
        ],
        [
            0,
            1,
            63,
            40,
            69,
            58,
            37,
            60,
            0
        ],
        [
            0,
            50,
            56,
            32,
            21,
            89,
            12,
            46,
            88,
            0
        ],
        [
            0,
            72,
            82,
            30,
            81,
            79,
            98,
            92,
            0
        ],
        [
            0,
            23,
            91,
            84,
            66,
            3,
            5,
            14,
            0
        ],
        [
            0,
            0
        ]
    ]
}