{
    "experiment_name": "problem_130_0.5",
    "run_index": 6,
    "execution_time": 57.02,
    "final_objective": 550048.2,
    "final_routes": [
        [
            0,
            80,
            31,
            68,
            88,
            103,
            24,
            39,
            0
        ],
        [
            0,
            89,
            60,
            10,
            53,
            71,
            26,
            93,
            18,
            112,
            55,
            0
        ],
        [
            0,
            33,
            111,
            117,
            84,
            79,
            49,
            116,
            76,
            87,
            100,
            107,
            0
        ],
        [
            0,
            44,
            43,
            82,
            54,
            29,
            51,
            113,
            15,
            105,
            64,
            0
        ],
        [
            0,
            40,
            98,
            50,
            91,
            66,
            4,
            21,
            126,
            95,
            83,
            41,
            36,
            0
        ],
        [
            0,
            32,
            35,
            92,
            14,
            85,
            9,
            122,
            1,
            73,
            25,
            118,
            58,
            12,
            124,
            115,
            0
        ],
        [
            0,
            70,
            11,
            37,
            57,
            99,
            56,
            28,
            16,
            30,
            96,
            110,
            5,
            94,
            90,
            8,
            77,
            0
        ],
        [
            0,
            42,
            3,
            104,
            7,
            62,
            75,
            127,
            22,
            108,
            69,
            13,
            102,
            72,
            0
        ],
        [
            0,
            46,
            125,
            48,
            121,
            52,
            78,
            128,
            129,
            97,
            27,
            20,
            0
        ],
        [
            0,
            19,
            38,
            123,
            86,
            2,
            47,
            106,
            120,
            101,
            119,
            61,
            74,
            63,
            109,
            0
        ],
        [
            0,
            45,
            6,
            23,
            67,
            59,
            114,
            34,
            65,
            81,
            17,
            0
        ]
    ]
}